display_server_interactions/__init__.py
display_server_interactions/__main__.py
display_server_interactions/base.py
display_server_interactions/image.py
display_server_interactions/linux.py
display_server_interactions/window.py
display_server_interactions-0.0.dev3.dist-info/LICENSE.txt
display_server_interactions-0.0.dev3.dist-info/METADATA
display_server_interactions-0.0.dev3.dist-info/WHEEL
display_server_interactions-0.0.dev3.dist-info/top_level.txt
display_server_interactions-0.0.dev3.dist-info/RECORD
