Metadata-Version: 2.1
Name: display-server-interactions
Version: 0.0.dev3
Summary: DSI allows you to perform basic interactions on your display server, like screenshotting a window or sending input to it.
Author: Commandcracker
License: Apache Software License
Project-URL: Documentation, https://display-server-interactions.readthedocs.io/en/latest/
Project-URL: Source, https://github.com/Commandcracker/display-server-interactions
Project-URL: Tracker, https://github.com/Commandcracker/display-server-interactions/issues
Keywords: screen,display,screenshot,input,window,screencapture,screengrab
Classifier: Development Status :: 2 - Pre-Alpha
Classifier: License :: OSI Approved :: Apache Software License
Classifier: Operating System :: POSIX :: Linux
Classifier: Programming Language :: Python :: 3
Classifier: Programming Language :: Python :: 3 :: Only
Classifier: Topic :: Multimedia :: Graphics
Classifier: Topic :: Multimedia :: Graphics :: Capture :: Screen Capture
License-File: LICENSE.txt
